{
  "GK": {
    "gkdiving": 0.21,
    "gkhandling": 0.21,
    "gkkicking": 0.05,
    "gkpositioning": 0.21,
    "gkreflexes": 0.21,
    "reactions": 0.11
  },
  "SW": {
    "aggression": 0.07,
    "ballcontrol": 0.04,
    "headingaccuracy": 0.1,
    "interceptions": 0.13,
    "jumping": 0.03,
    "marking": 0.14,
    "reactions": 0.05,
    "shortpassing": 0.05,
    "slidingtackle": 0.1,
    "sprintspeed": 0.02,
    "standingtackle": 0.17,
    "strength": 0.1
  },
  "RWB": {
    "acceleration": 0.04,
    "ballcontrol": 0.08,
    "crossing": 0.12,
    "dribbling": 0.04,
    "interceptions": 0.12,
    "marking": 0.07,
    "reactions": 0.08,
    "shortpassing": 0.1,
    "slidingtackle": 0.11,
    "sprintspeed": 0.06,
    "stamina": 0.1,
    "standingtackle": 0.08
  },
  "RB": {
    "acceleration": 0.05,
    "ballcontrol": 0.07,
    "crossing": 0.09,
    "headingaccuracy": 0.04,
    "interceptions": 0.12,
    "marking": 0.08,
    "reactions": 0.08,
    "shortpassing": 0.07,
    "slidingtackle": 0.14,
    "sprintspeed": 0.07,
    "stamina": 0.08,
    "standingtackle": 0.11
  },
  "RCB": {
    "aggression": 0.07,
    "ballcontrol": 0.04,
    "headingaccuracy": 0.1,
    "interceptions": 0.13,
    "jumping": 0.03,
    "marking": 0.14,
    "reactions": 0.05,
    "shortpassing": 0.05,
    "slidingtackle": 0.1,
    "sprintspeed": 0.02,
    "standingtackle": 0.17,
    "strength": 0.1
  },
  "CB": {
    "aggression": 0.07,
    "ballcontrol": 0.04,
    "headingaccuracy": 0.1,
    "interceptions": 0.13,
    "jumping": 0.03,
    "marking": 0.14,
    "reactions": 0.05,
    "shortpassing": 0.05,
    "slidingtackle": 0.1,
    "sprintspeed": 0.02,
    "standingtackle": 0.17,
    "strength": 0.1
  },
  "LCB": {
    "aggression": 0.07,
    "ballcontrol": 0.04,
    "headingaccuracy": 0.1,
    "interceptions": 0.13,
    "jumping": 0.03,
    "marking": 0.14,
    "reactions": 0.05,
    "shortpassing": 0.05,
    "slidingtackle": 0.1,
    "sprintspeed": 0.02,
    "standingtackle": 0.17,
    "strength": 0.1
  },
  "LB": {
    "acceleration": 0.05,
    "ballcontrol": 0.07,
    "crossing": 0.09,
    "headingaccuracy": 0.04,
    "interceptions": 0.12,
    "marking": 0.08,
    "reactions": 0.08,
    "shortpassing": 0.07,
    "slidingtackle": 0.14,
    "sprintspeed": 0.07,
    "stamina": 0.08,
    "standingtackle": 0.11
  },
  "LWB": {
    "acceleration": 0.04,
    "ballcontrol": 0.08,
    "crossing": 0.12,
    "dribbling": 0.04,
    "interceptions": 0.12,
    "marking": 0.07,
    "reactions": 0.08,
    "shortpassing": 0.1,
    "slidingtackle": 0.11,
    "sprintspeed": 0.06,
    "stamina": 0.1,
    "standingtackle": 0.08
  },
  "RDM": {
    "aggression": 0.05,
    "ballcontrol": 0.1,
    "interceptions": 0.14,
    "longpassing": 0.1,
    "marking": 0.09,
    "reactions": 0.07,
    "shortpassing": 0.14,
    "slidingtackle": 0.05,
    "stamina": 0.06,
    "standingtackle": 0.12,
    "strength": 0.04,
    "vision": 0.04
  },
  "CDM": {
    "ballcontrol": 0.14,
    "dribbling": 0.07,
    "finishing": 0.02,
    "interceptions": 0.05,
    "longpassing": 0.13,
    "longshots": 0.04,
    "positioning": 0.06,
    "reactions": 0.08,
    "shortpassing": 0.17,
    "stamina": 0.06,
    "standingtackle": 0.05,
    "vision": 0.13
  },
  "LDM": {
    "aggression": 0.05,
    "ballcontrol": 0.1,
    "interceptions": 0.14,
    "longpassing": 0.1,
    "marking": 0.09,
    "reactions": 0.07,
    "shortpassing": 0.14,
    "slidingtackle": 0.05,
    "stamina": 0.06,
    "standingtackle": 0.12,
    "strength": 0.04,
    "vision": 0.04
  },
  "RM": {
    "acceleration": 0.07,
    "ballcontrol": 0.13,
    "crossing": 0.1,
    "dribbling": 0.15,
    "finishing": 0.06,
    "longpassing": 0.05,
    "positioning": 0.08,
    "reactions": 0.07,
    "shortpassing": 0.11,
    "sprintspeed": 0.06,
    "stamina": 0.05,
    "vision": 0.07
  },
  "RCM": {
    "acceleration": 0.04,
    "agility": 0.03,
    "ballcontrol": 0.15,
    "dribbling": 0.13,
    "finishing": 0.07,
    "longpassing": 0.04,
    "longshots": 0.05,
    "positioning": 0.09,
    "reactions": 0.07,
    "shortpassing": 0.16,
    "sprintspeed": 0.03,
    "vision": 0.14
  },
  "CM": {
    "ballcontrol": 0.14,
    "dribbling": 0.07,
    "finishing": 0.02,
    "interceptions": 0.05,
    "longpassing": 0.13,
    "longshots": 0.04,
    "positioning": 0.06,
    "reactions": 0.08,
    "shortpassing": 0.17,
    "stamina": 0.06,
    "standingtackle": 0.05,
    "vision": 0.13
  },
  "LCM": {
    "ballcontrol": 0.14,
    "dribbling": 0.07,
    "finishing": 0.02,
    "interceptions": 0.05,
    "longpassing": 0.13,
    "longshots": 0.04,
    "positioning": 0.06,
    "reactions": 0.08,
    "shortpassing": 0.17,
    "stamina": 0.06,
    "standingtackle": 0.05,
    "vision": 0.13
  },
  "LM": {
    "acceleration": 0.07,
    "ballcontrol": 0.13,
    "crossing": 0.1,
    "dribbling": 0.15,
    "finishing": 0.06,
    "longpassing": 0.05,
    "positioning": 0.08,
    "reactions": 0.07,
    "shortpassing": 0.11,
    "sprintspeed": 0.06,
    "stamina": 0.05,
    "vision": 0.07
  },
  "RAM": {
    "acceleration": 0.04,
    "agility": 0.03,
    "ballcontrol": 0.15,
    "dribbling": 0.13,
    "finishing": 0.07,
    "longpassing": 0.04,
    "longshots": 0.05,
    "positioning": 0.09,
    "reactions": 0.07,
    "shortpassing": 0.16,
    "sprintspeed": 0.03,
    "vision": 0.14
  },
  "CAM": {
    "acceleration": 0.04,
    "agility": 0.03,
    "ballcontrol": 0.15,
    "dribbling": 0.13,
    "finishing": 0.07,
    "longpassing": 0.04,
    "longshots": 0.05,
    "positioning": 0.09,
    "reactions": 0.07,
    "shortpassing": 0.16,
    "sprintspeed": 0.03,
    "vision": 0.14
  },
  "LAM": {
    "acceleration": 0.05,
    "ballcontrol": 0.15,
    "dribbling": 0.14,
    "finishing": 0.11,
    "headingaccuracy": 0.02,
    "longshots": 0.04,
    "positioning": 0.13,
    "reactions": 0.09,
    "shortpassing": 0.09,
    "shotpower": 0.05,
    "sprintspeed": 0.05,
    "vision": 0.08
  },
  "RF": {
    "acceleration": 0.05,
    "ballcontrol": 0.15,
    "dribbling": 0.14,
    "finishing": 0.11,
    "headingaccuracy": 0.02,
    "longshots": 0.04,
    "positioning": 0.13,
    "reactions": 0.09,
    "shortpassing": 0.09,
    "shotpower": 0.05,
    "sprintspeed": 0.05,
    "vision": 0.08
  },
  "CF": {
    "acceleration": 0.04,
    "ballcontrol": 0.1,
    "dribbling": 0.07,
    "finishing": 0.18,
    "headingaccuracy": 0.1,
    "longshots": 0.03,
    "positioning": 0.13,
    "reactions": 0.08,
    "shortpassing": 0.05,
    "shotpower": 0.1,
    "sprintspeed": 0.05,
    "strength": 0.05,
    "volleys": 0.02
  },
  "LF": {
    "acceleration": 0.05,
    "ballcontrol": 0.15,
    "dribbling": 0.14,
    "finishing": 0.11,
    "headingaccuracy": 0.02,
    "longshots": 0.04,
    "positioning": 0.13,
    "reactions": 0.09,
    "shortpassing": 0.09,
    "shotpower": 0.05,
    "sprintspeed": 0.05,
    "vision": 0.08
  },
  "RW": {
    "acceleration": 0.07,
    "agility": 0.03,
    "ballcontrol": 0.14,
    "crossing": 0.09,
    "dribbling": 0.16,
    "finishing": 0.1,
    "longshots": 0.04,
    "positioning": 0.09,
    "reactions": 0.07,
    "shortpassing": 0.09,
    "sprintspeed": 0.06,
    "vision": 0.06
  },
  "RS": {
    "acceleration": 0.04,
    "ballcontrol": 0.1,
    "dribbling": 0.07,
    "finishing": 0.18,
    "headingaccuracy": 0.1,
    "longshots": 0.03,
    "positioning": 0.13,
    "reactions": 0.08,
    "shortpassing": 0.05,
    "shotpower": 0.1,
    "sprintspeed": 0.05,
    "strength": 0.05,
    "volleys": 0.02
  },
  "ST": {
    "acceleration": 0.04,
    "ballcontrol": 0.1,
    "dribbling": 0.07,
    "finishing": 0.18,
    "headingaccuracy": 0.1,
    "longshots": 0.03,
    "positioning": 0.13,
    "reactions": 0.08,
    "shortpassing": 0.05,
    "shotpower": 0.1,
    "sprintspeed": 0.05,
    "strength": 0.05,
    "volleys": 0.02
  },
  "LS": {
    "acceleration": 0.04,
    "ballcontrol": 0.1,
    "dribbling": 0.07,
    "finishing": 0.18,
    "headingaccuracy": 0.1,
    "longshots": 0.03,
    "positioning": 0.13,
    "reactions": 0.08,
    "shortpassing": 0.05,
    "shotpower": 0.1,
    "sprintspeed": 0.05,
    "strength": 0.05,
    "volleys": 0.02
  },
  "LW": {
    "acceleration": 0.07,
    "agility": 0.03,
    "ballcontrol": 0.14,
    "crossing": 0.09,
    "dribbling": 0.16,
    "finishing": 0.1,
    "longshots": 0.04,
    "positioning": 0.09,
    "reactions": 0.07,
    "shortpassing": 0.09,
    "sprintspeed": 0.06,
    "vision": 0.06
  }
}
